COPYING
MANIFEST.in
README.md
ns-convert
setup.cfg
setup.py
capi/nsAPIdllimp.h
capi/nsAPItypes.h
capi/nspy_glue.c
doc/Makefile
doc/make.bat
doc/source/conf.py
doc/source/index.rst
doc/source/_static/data_schema.png
doc/source/_static/entities.png
doc/source/_static/gnode_logo.png
doc/source/_themes/.gitignore
doc/source/_themes/LICENSE
doc/source/_themes/README.md
doc/source/_themes/gnode_theme_support.py
doc/source/_themes/gnode/layout.html
doc/source/_themes/gnode/relations.html
doc/source/_themes/gnode/theme.conf
doc/source/_themes/gnode/static/flasky.css_t
doc/source/_themes/gnode/static/small_flask.css
doc/source/_themes/gnode_small/layout.html
doc/source/_themes/gnode_small/theme.conf
doc/source/_themes/gnode_small/static/flasky.css_t
neuroshare/AnalogEntity.py
neuroshare/Entity.py
neuroshare/EventEntity.py
neuroshare/File.py
neuroshare/Library.py
neuroshare/NeuralEntity.py
neuroshare/SegmentEntity.py
neuroshare/__init__.py
neuroshare.egg-info/PKG-INFO
neuroshare.egg-info/SOURCES.txt
neuroshare.egg-info/dependency_links.txt
neuroshare.egg-info/top_level.txt