Metadata-Version: 1.1
Name: neuroshare
Version: 0.9.3
Summary: Python Bindings for Neuroshare
Home-page: http://www.g-node.org/neuroshare-tools
Author: Christian Kellner
Author-email: kellner@biologie.uni-muenchen.de
License: LGPL
Keywords: neuroshare,neuroscience,science
Platform: Windows
Platform: Linux
Platform: Solaris
Platform: Mac OS-X
Platform: Unix
Classifier: Development Status :: 5 - Production/Stable
Classifier: Programming Language :: Python
Classifier: Programming Language :: C
Classifier: License :: OSI Approved :: GNU Library or Lesser General Public License (LGPL)
Classifier: Operating System :: OS Independent
Classifier: Intended Audience :: Developers
Classifier: Topic :: Scientific/Engineering
Classifier: Topic :: Software Development :: Libraries :: Python Modules
